easyfederated/__init__.py
easyfederated/build/__init__.py
easyfederated/build/flare.py
easyfederated/build/nix.py
easyfederated/build/ssh.py
easyfederated/build/uv.py
easyfederated/cli/__init__.py
easyfederated/cli/app.py
easyfederated/cli/commands/__init__.py
easyfederated/cli/commands/clean.py
easyfederated/cli/commands/start.py
easyfederated/cli/commands/status.py
easyfederated/cli/commands/stop.py
easyfederated/common/__init__.py
easyfederated/common/config.py
easyfederated/common/errors.py
easyfederated/common/logger.py
easyfederated/common/machines.py
easyfederated/common/project.py
easyfederated/common/state.py
easyfederated/lib/__init__.py
easyfederated/lib/config.py
easyfederated/lib/constants.py
easyfederated/lib/easyfed.py
easyfederated/lib/job.py
easyfederated/lib/backends/__init__.py
easyfederated/lib/backends/numpy.py
easyfederated/lib/backends/torch.py
easyfederated-0.1.5.dist-info/METADATA
easyfederated-0.1.5.dist-info/WHEEL
easyfederated-0.1.5.dist-info/entry_points.txt
easyfederated-0.1.5.dist-info/RECORD
