Metadata-Version: 2.4
Name: easyfederated
Version: 0.1.5
Summary: Tool for automatizing the deployment of easy federated learning examples
Requires-Python: >=3.12
Requires-Dist: checksumdir>=1.3.0
Requires-Dist: dacite>=1.9.2
Requires-Dist: nvflare[dev]>=2.6.2
Requires-Dist: paramiko>=4.0.0
Requires-Dist: tqdm>=4.67.1
Requires-Dist: typer>=0.19.2
